{"nodes": [{"id": "stm32h743", "label": "STM32H743 MCU", "file_type": "document", "source_file": "10_Wiki/exosuit/stm32h743.md", "source_location": null, "source_url": null, "captured_at": null, "author": null, "contributor": null}, {"id": "stm32h743_cortex_m7", "label": "STM32H743 Cortex-M7 @ 480MHz", "file_type": "document", "source_file": "10_Wiki/exosuit/stm32h743.md", "source_location": null, "source_url": null, "captured_at": null, "author": null, "contributor": null}, {"id": "canopen_master_implementation", "label": "CANopen Master Implementation", "file_type": "document", "source_file": "10_Wiki/exosuit/stm32h743.md", "source_location": null, "source_url": null, "captured_at": null, "author": null, "contributor": null}, {"id": "teensy_4_1", "label": "Teensy 4.1 MCU", "file_type": "document", "source_file": "10_Wiki/exosuit/stm32h743.md", "source_location": null, "source_url": null, "captured_at": null, "author": null, "contributor": null}], "edges": [{"source": "stm32h743", "target": "stm32h743_cortex_m7", "relation": "implements", "confidence": "EXTRACTED", "confidence_score": 1.0, "source_file": "10_Wiki/exosuit/stm32h743.md", "source_location": "\u00a7 Brief Summary", "weight": 1.0}, {"source": "stm32h743", "target": "canopen_master_implementation", "relation": "implements", "confidence": "EXTRACTED", "confidence_score": 1.0, "source_file": "10_Wiki/exosuit/stm32h743.md", "source_location": "\uc6a9\ub3c4 \ud6c4\ubcf4: CANopenNode \ub9c8\uc2a4\ud130", "weight": 1.0}, {"source": "stm32h743", "target": "elmo_gold_twitter", "relation": "conceptually_related_to", "confidence": "EXTRACTED", "confidence_score": 1.0, "source_file": "10_Wiki/exosuit/stm32h743.md", "source_location": "[[elmo-gold-twitter]] \uc5f0\ub3d9", "weight": 1.0}, {"source": "stm32h743", "target": "teensy_4_1", "relation": "conceptually_related_to", "confidence": "EXTRACTED", "confidence_score": 1.0, "source_file": "10_Wiki/exosuit/stm32h743.md", "source_location": "\ube44\uad50: [[teensy-4-1]] vs STM32H743", "weight": 1.0}], "hyperedges": []}