{"nodes": [{"id": "perception_pipeline_wrap_up", "label": "Perception Pipeline Wrap-Up", "file_type": "document", "source_file": "00_Raw/2026-04-18-perception-pipeline-wrap-up.md", "captured_at": "2026-04-18", "author": "ChoByeongJun"}, {"id": "method_a_standing_calib", "label": "Method A: Standing Calibration", "file_type": "concept", "source_file": "00_Raw/2026-04-18-perception-pipeline-wrap-up.md", "captured_at": "2026-04-18"}, {"id": "method_b_imu_world_frame", "label": "Method B: IMU World Frame", "file_type": "concept", "source_file": "00_Raw/2026-04-18-perception-pipeline-wrap-up.md", "captured_at": "2026-04-18"}, {"id": "teensy_4_1", "label": "Teensy 4.1 Microcontroller", "file_type": "artifact", "source_file": "00_Raw/2026-04-18-perception-pipeline-wrap-up.md", "captured_at": "2026-04-18"}, {"id": "p99_latency_17ms", "label": "p99 Latency 17ms (stable)", "file_type": "concept", "source_file": "00_Raw/2026-04-18-perception-pipeline-wrap-up.md", "captured_at": "2026-04-18"}, {"id": "bone_length_stability", "label": "Bone Length Stability Logging", "file_type": "concept", "source_file": "00_Raw/2026-04-18-perception-pipeline-wrap-up.md", "captured_at": "2026-04-18"}, {"id": "gdm_off_failure", "label": "GDM Off FATAL Failure (GMSL segfault)", "file_type": "concept", "source_file": "00_Raw/2026-04-18-perception-pipeline-wrap-up.md", "captured_at": "2026-04-18"}, {"id": "neural_depth_rejection", "label": "NEURAL Depth Mode Rejection", "file_type": "concept", "source_file": "00_Raw/2026-04-18-perception-pipeline-wrap-up.md", "captured_at": "2026-04-18"}], "edges": [{"source": "latency_13_7ms_final", "target": "p99_latency_17ms", "relation": "conceptually_related_to", "confidence": "EXTRACTED", "confidence_score": 1.0, "source_file": "00_Raw/2026-04-18-perception-pipeline-wrap-up.md", "weight": 1.0}, {"source": "method_b_imu_world_frame", "target": "skip_imu", "relation": "conceptually_related_to", "confidence": "EXTRACTED", "confidence_score": 1.0, "source_file": "00_Raw/2026-04-18-perception-pipeline-wrap-up.md", "weight": 1.0}, {"source": "gdm_off_failure", "target": "neural_depth_rejection", "relation": "conceptually_related_to", "confidence": "EXTRACTED", "confidence_score": 1.0, "source_file": "00_Raw/2026-04-18-perception-pipeline-wrap-up.md", "weight": 1.0}, {"source": "hard_limit_frame_skip", "target": "teensy_4_1", "relation": "rationale_for", "confidence": "INFERRED", "confidence_score": 0.7, "source_file": "00_Raw/2026-04-18-perception-pipeline-wrap-up.md", "weight": 1.0}], "hyperedges": []}